[
  {
    "StartDate": "2024-09-28T17:37:22",
    "EndDate": "2023-10-15T16:18:25",
    "CustomerId": 626
  },
  {
    "StartDate": "2023-11-07T21:01:45",
    "EndDate": "2023-08-19T22:18:37",
    "CustomerId": 124
  },
  {
    "StartDate": "2024-08-03T05:18:12",
    "EndDate": "2025-01-01T23:41:14",
    "CustomerId": 488
  },
  {
    "StartDate": "2024-12-29T21:45:47",
    "EndDate": "2025-01-24T00:05:43",
    "CustomerId": 606
  },
  {
    "StartDate": "2024-04-05T11:18:52",
    "EndDate": "2024-01-09T10:58:18",
    "CustomerId": 463
  },
  {
    "StartDate": "2024-06-06T14:50:23",
    "EndDate": "2023-10-19T00:17:48",
    "CustomerId": 492
  },
  {
    "StartDate": "2024-05-02T15:26:56",
    "EndDate": "2024-06-26T05:35:10",
    "CustomerId": 149
  },
  {
    "StartDate": "2024-03-12T03:37:02",
    "EndDate": "2024-12-17T10:09:23",
    "CustomerId": 387
  },
  {
    "StartDate": "2025-07-14T07:54:15",
    "EndDate": "2024-03-04T11:56:13",
    "CustomerId": 435
  },
  {
    "StartDate": "2025-03-31T07:06:43",
    "EndDate": "2023-08-01T10:50:19",
    "CustomerId": 848
  },
  {
    "StartDate": "2023-09-04T13:01:23",
    "EndDate": "2025-02-07T09:15:18",
    "CustomerId": 54
  },
  {
    "StartDate": "2025-01-13T01:08:53",
    "EndDate": "2023-10-11T10:05:21",
    "CustomerId": 71
  },
  {
    "StartDate": "2025-02-23T06:57:25",
    "EndDate": "2025-01-21T23:59:59",
    "CustomerId": 88
  },
  {
    "StartDate": "2023-12-07T17:47:14",
    "EndDate": "2024-12-22T06:17:15",
    "CustomerId": 502
  },
  {
    "StartDate": "2023-10-07T17:12:02",
    "EndDate": "2025-06-16T17:22:19",
    "CustomerId": 489
  },
  {
    "StartDate": "2023-12-23T03:21:48",
    "EndDate": "2023-10-27T13:36:17",
    "CustomerId": 622
  },
  {
    "StartDate": "2025-05-09T00:11:16",
    "EndDate": "2024-06-22T00:15:02",
    "CustomerId": 964
  },
  {
    "StartDate": "2025-05-27T02:30:57",
    "EndDate": "2024-06-07T03:13:21",
    "CustomerId": 421
  },
  {
    "StartDate": "2024-06-21T18:45:02",
    "EndDate": "2024-10-09T16:25:30",
    "CustomerId": 215
  },
  {
    "StartDate": "2023-08-13T01:12:05",
    "EndDate": "2024-04-28T20:24:13",
    "CustomerId": 296
  },
  {
    "StartDate": "2024-07-11T21:27:22",
    "EndDate": "2024-04-08T14:33:41",
    "CustomerId": 817
  },
  {
    "StartDate": "2023-07-26T07:40:03",
    "EndDate": "2025-03-28T21:25:15",
    "CustomerId": 896
  },
  {
    "StartDate": "2023-10-19T10:47:09",
    "EndDate": "2023-11-25T12:52:51",
    "CustomerId": 993
  },
  {
    "StartDate": "2024-11-07T16:30:51",
    "EndDate": "2024-11-20T15:53:03",
    "CustomerId": 382
  },
  {
    "StartDate": "2024-09-20T17:56:28",
    "EndDate": "2025-05-06T03:46:40",
    "CustomerId": 753
  },
  {
    "StartDate": "2025-07-14T21:34:44",
    "EndDate": "2023-08-02T22:16:58",
    "CustomerId": 33
  },
  {
    "StartDate": "2024-12-01T15:18:43",
    "EndDate": "2025-05-16T21:49:52",
    "CustomerId": 410
  },
  {
    "StartDate": "2023-08-03T09:34:29",
    "EndDate": "2025-02-05T11:16:11",
    "CustomerId": 538
  },
  {
    "StartDate": "2024-05-04T21:27:31",
    "EndDate": "2025-06-16T10:17:18",
    "CustomerId": 414
  },
  {
    "StartDate": "2024-01-21T20:21:27",
    "EndDate": "2024-01-16T23:59:35",
    "CustomerId": 655
  },
  {
    "StartDate": "2025-04-02T09:36:04",
    "EndDate": "2024-07-03T09:52:17",
    "CustomerId": 696
  },
  {
    "StartDate": "2023-07-21T23:04:08",
    "EndDate": "2023-12-24T15:14:47",
    "CustomerId": 905
  },
  {
    "StartDate": "2024-10-11T15:43:09",
    "EndDate": "2023-10-28T03:44:44",
    "CustomerId": 615
  },
  {
    "StartDate": "2025-02-24T09:14:46",
    "EndDate": "2023-10-08T23:12:32",
    "CustomerId": 3
  },
  {
    "StartDate": "2024-08-28T18:17:47",
    "EndDate": "2024-02-02T11:49:42",
    "CustomerId": 262
  },
  {
    "StartDate": "2024-10-29T22:14:23",
    "EndDate": "2025-03-09T05:09:03",
    "CustomerId": 511
  },
  {
    "StartDate": "2025-02-13T16:21:25",
    "EndDate": "2024-01-15T16:40:02",
    "CustomerId": 573
  },
  {
    "StartDate": "2023-09-01T20:37:44",
    "EndDate": "2025-07-18T18:48:59",
    "CustomerId": 766
  },
  {
    "StartDate": "2024-01-06T01:57:55",
    "EndDate": "2024-11-10T01:31:40",
    "CustomerId": 739
  },
  {
    "StartDate": "2024-05-11T18:05:34",
    "EndDate": "2024-08-28T14:27:08",
    "CustomerId": 296
  },
  {
    "StartDate": "2025-02-02T03:13:39",
    "EndDate": "2024-10-08T20:04:19",
    "CustomerId": 357
  },
  {
    "StartDate": "2023-08-26T17:16:01",
    "EndDate": "2024-09-09T08:48:30",
    "CustomerId": 719
  },
  {
    "StartDate": "2024-03-23T20:10:13",
    "EndDate": "2023-10-11T15:28:32",
    "CustomerId": 686
  },
  {
    "StartDate": "2024-03-21T07:25:26",
    "EndDate": "2024-08-07T20:49:25",
    "CustomerId": 99
  },
  {
    "StartDate": "2024-09-16T08:27:00",
    "EndDate": "2025-05-05T10:16:07",
    "CustomerId": 383
  },
  {
    "StartDate": "2024-04-01T13:29:45",
    "EndDate": "2025-05-22T14:03:34",
    "CustomerId": 994
  },
  {
    "StartDate": "2025-04-24T13:18:04",
    "EndDate": "2025-05-23T05:32:20",
    "CustomerId": 350
  },
  {
    "StartDate": "2023-07-28T03:37:58",
    "EndDate": "2025-02-26T15:22:01",
    "CustomerId": 985
  },
  {
    "StartDate": "2023-12-30T11:45:18",
    "EndDate": "2023-10-12T09:48:09",
    "CustomerId": 936
  },
  {
    "StartDate": "2024-10-14T00:38:09",
    "EndDate": "2025-03-28T18:41:43",
    "CustomerId": 56
  },
  {
    "StartDate": "2025-05-09T18:44:54",
    "EndDate": "2024-10-02T01:28:08",
    "CustomerId": 829
  },
  {
    "StartDate": "2024-12-04T10:40:15",
    "EndDate": "2024-08-12T16:12:00",
    "CustomerId": 364
  },
  {
    "StartDate": "2023-10-17T17:40:11",
    "EndDate": "2024-01-20T07:51:23",
    "CustomerId": 646
  },
  {
    "StartDate": "2024-06-18T16:14:56",
    "EndDate": "2024-04-10T21:19:53",
    "CustomerId": 331
  },
  {
    "StartDate": "2024-03-16T23:57:54",
    "EndDate": "2024-08-26T16:52:59",
    "CustomerId": 21
  },
  {
    "StartDate": "2024-12-22T05:40:45",
    "EndDate": "2025-03-15T08:25:08",
    "CustomerId": 547
  },
  {
    "StartDate": "2023-09-20T10:34:13",
    "EndDate": "2024-10-07T11:06:45",
    "CustomerId": 582
  },
  {
    "StartDate": "2024-07-01T01:54:36",
    "EndDate": "2023-08-06T15:43:25",
    "CustomerId": 304
  },
  {
    "StartDate": "2024-05-22T18:29:50",
    "EndDate": "2023-09-07T17:25:02",
    "CustomerId": 850
  },
  {
    "StartDate": "2025-01-18T12:31:29",
    "EndDate": "2023-08-24T18:28:58",
    "CustomerId": 703
  },
  {
    "StartDate": "2023-09-10T03:23:14",
    "EndDate": "2023-12-06T06:08:28",
    "CustomerId": 354
  },
  {
    "StartDate": "2024-05-03T03:39:40",
    "EndDate": "2024-05-22T20:20:47",
    "CustomerId": 449
  },
  {
    "StartDate": "2025-03-08T03:31:20",
    "EndDate": "2023-08-12T15:24:03",
    "CustomerId": 816
  },
  {
    "StartDate": "2023-07-30T22:39:21",
    "EndDate": "2023-09-09T17:54:05",
    "CustomerId": 17
  },
  {
    "StartDate": "2024-03-24T13:30:59",
    "EndDate": "2025-06-12T01:23:21",
    "CustomerId": 30
  },
  {
    "StartDate": "2025-04-24T09:02:12",
    "EndDate": "2025-04-18T20:44:30",
    "CustomerId": 585
  },
  {
    "StartDate": "2025-01-30T17:01:01",
    "EndDate": "2024-04-17T13:03:00",
    "CustomerId": 655
  },
  {
    "StartDate": "2024-12-20T18:05:36",
    "EndDate": "2024-10-09T07:29:17",
    "CustomerId": 251
  },
  {
    "StartDate": "2025-05-06T14:17:51",
    "EndDate": "2023-09-06T12:41:00",
    "CustomerId": 587
  },
  {
    "StartDate": "2024-10-23T13:32:15",
    "EndDate": "2024-11-01T04:11:50",
    "CustomerId": 29
  },
  {
    "StartDate": "2025-03-11T01:01:40",
    "EndDate": "2024-06-20T14:16:57",
    "CustomerId": 204
  },
  {
    "StartDate": "2025-06-20T08:55:58",
    "EndDate": "2025-03-24T11:58:10",
    "CustomerId": 734
  },
  {
    "StartDate": "2024-02-12T11:24:54",
    "EndDate": "2023-10-18T10:18:50",
    "CustomerId": 485
  },
  {
    "StartDate": "2025-02-08T15:11:27",
    "EndDate": "2023-09-28T09:50:34",
    "CustomerId": 14
  },
  {
    "StartDate": "2024-04-05T09:29:52",
    "EndDate": "2025-03-05T00:40:42",
    "CustomerId": 686
  },
  {
    "StartDate": "2024-11-17T13:47:24",
    "EndDate": "2023-09-12T21:34:17",
    "CustomerId": 87
  },
  {
    "StartDate": "2025-04-06T09:42:26",
    "EndDate": "2024-08-11T05:41:13",
    "CustomerId": 531
  },
  {
    "StartDate": "2025-07-20T16:06:35",
    "EndDate": "2025-03-09T14:20:45",
    "CustomerId": 648
  },
  {
    "StartDate": "2025-04-19T12:11:58",
    "EndDate": "2025-03-06T04:52:46",
    "CustomerId": 164
  },
  {
    "StartDate": "2023-12-13T18:08:33",
    "EndDate": "2025-05-30T04:02:33",
    "CustomerId": 992
  },
  {
    "StartDate": "2025-01-04T21:23:09",
    "EndDate": "2025-02-13T05:49:43",
    "CustomerId": 910
  },
  {
    "StartDate": "2025-03-04T19:49:36",
    "EndDate": "2023-09-02T00:08:41",
    "CustomerId": 82
  },
  {
    "StartDate": "2024-01-15T02:57:20",
    "EndDate": "2025-04-21T05:45:20",
    "CustomerId": 825
  },
  {
    "StartDate": "2024-12-30T04:20:17",
    "EndDate": "2025-04-21T08:30:27",
    "CustomerId": 754
  },
  {
    "StartDate": "2024-12-21T13:35:28",
    "EndDate": "2025-01-10T16:44:45",
    "CustomerId": 625
  },
  {
    "StartDate": "2024-07-31T16:53:56",
    "EndDate": "2024-07-27T07:45:21",
    "CustomerId": 328
  },
  {
    "StartDate": "2025-05-17T19:02:37",
    "EndDate": "2024-03-17T20:11:18",
    "CustomerId": 624
  },
  {
    "StartDate": "2024-01-06T22:04:55",
    "EndDate": "2023-12-29T21:53:38",
    "CustomerId": 63
  },
  {
    "StartDate": "2023-11-28T19:03:37",
    "EndDate": "2024-04-17T03:35:03",
    "CustomerId": 860
  },
  {
    "StartDate": "2024-09-18T18:58:38",
    "EndDate": "2024-08-03T08:51:44",
    "CustomerId": 434
  },
  {
    "StartDate": "2024-09-29T11:59:22",
    "EndDate": "2024-12-31T10:32:41",
    "CustomerId": 101
  },
  {
    "StartDate": "2023-10-26T22:13:08",
    "EndDate": "2023-11-11T02:23:49",
    "CustomerId": 300
  },
  {
    "StartDate": "2024-09-16T14:59:33",
    "EndDate": "2024-12-23T04:13:03",
    "CustomerId": 811
  },
  {
    "StartDate": "2023-11-25T08:21:26",
    "EndDate": "2024-06-03T08:27:43",
    "CustomerId": 16
  },
  {
    "StartDate": "2025-07-02T23:19:57",
    "EndDate": "2023-08-08T08:22:47",
    "CustomerId": 430
  },
  {
    "StartDate": "2024-02-27T12:53:32",
    "EndDate": "2025-07-15T19:17:32",
    "CustomerId": 965
  },
  {
    "StartDate": "2023-09-23T23:43:14",
    "EndDate": "2024-07-29T00:01:56",
    "CustomerId": 807
  },
  {
    "StartDate": "2024-04-27T16:50:19",
    "EndDate": "2023-11-27T02:58:09",
    "CustomerId": 294
  },
  {
    "StartDate": "2024-07-03T16:24:14",
    "EndDate": "2024-07-23T19:15:33",
    "CustomerId": 421
  },
  {
    "StartDate": "2023-11-23T20:15:03",
    "EndDate": "2024-06-08T21:44:57",
    "CustomerId": 886
  },
  {
    "StartDate": "2024-04-27T12:07:39",
    "EndDate": "2025-04-08T01:53:55",
    "CustomerId": 800
  },
  {
    "StartDate": "2023-10-14T19:08:02",
    "EndDate": "2024-12-18T14:23:54",
    "CustomerId": 310
  },
  {
    "StartDate": "2025-04-25T06:15:23",
    "EndDate": "2025-04-02T08:28:48",
    "CustomerId": 930
  },
  {
    "StartDate": "2024-12-31T01:23:03",
    "EndDate": "2024-04-13T05:26:45",
    "CustomerId": 826
  },
  {
    "StartDate": "2024-11-07T21:41:08",
    "EndDate": "2024-06-06T02:30:35",
    "CustomerId": 930
  },
  {
    "StartDate": "2023-12-10T17:59:48",
    "EndDate": "2023-07-26T20:53:30",
    "CustomerId": 887
  },
  {
    "StartDate": "2024-04-13T22:50:33",
    "EndDate": "2025-07-03T06:00:52",
    "CustomerId": 692
  },
  {
    "StartDate": "2025-06-02T11:19:34",
    "EndDate": "2023-12-22T23:39:28",
    "CustomerId": 166
  },
  {
    "StartDate": "2024-09-26T08:17:26",
    "EndDate": "2025-06-10T19:29:04",
    "CustomerId": 702
  },
  {
    "StartDate": "2025-01-03T06:47:09",
    "EndDate": "2024-10-21T13:03:13",
    "CustomerId": 613
  },
  {
    "StartDate": "2024-12-17T12:04:51",
    "EndDate": "2025-06-04T10:41:15",
    "CustomerId": 381
  },
  {
    "StartDate": "2024-08-17T01:18:00",
    "EndDate": "2024-10-04T14:08:36",
    "CustomerId": 107
  },
  {
    "StartDate": "2024-07-24T04:35:33",
    "EndDate": "2025-04-29T17:10:22",
    "CustomerId": 472
  },
  {
    "StartDate": "2024-09-27T17:36:06",
    "EndDate": "2024-07-13T10:21:17",
    "CustomerId": 758
  },
  {
    "StartDate": "2024-11-13T08:43:37",
    "EndDate": "2025-07-04T17:42:42",
    "CustomerId": 839
  },
  {
    "StartDate": "2023-10-03T17:49:31",
    "EndDate": "2024-09-02T13:13:32",
    "CustomerId": 97
  },
  {
    "StartDate": "2024-09-25T01:21:29",
    "EndDate": "2025-04-16T10:40:25",
    "CustomerId": 388
  },
  {
    "StartDate": "2025-03-18T20:29:27",
    "EndDate": "2025-06-14T22:25:34",
    "CustomerId": 899
  },
  {
    "StartDate": "2024-03-05T10:39:39",
    "EndDate": "2024-12-18T18:53:17",
    "CustomerId": 42
  },
  {
    "StartDate": "2024-11-19T00:32:35",
    "EndDate": "2024-08-25T02:38:30",
    "CustomerId": 9
  },
  {
    "StartDate": "2025-07-07T18:53:14",
    "EndDate": "2025-06-30T01:35:09",
    "CustomerId": 964
  },
  {
    "StartDate": "2023-12-05T08:31:05",
    "EndDate": "2024-10-10T20:48:40",
    "CustomerId": 327
  },
  {
    "StartDate": "2023-12-29T05:49:11",
    "EndDate": "2024-02-24T18:57:25",
    "CustomerId": 991
  },
  {
    "StartDate": "2024-11-16T06:55:42",
    "EndDate": "2025-05-29T12:09:30",
    "CustomerId": 726
  },
  {
    "StartDate": "2024-05-23T18:28:17",
    "EndDate": "2023-10-29T08:21:09",
    "CustomerId": 323
  },
  {
    "StartDate": "2023-07-30T09:27:06",
    "EndDate": "2023-12-22T16:48:53",
    "CustomerId": 447
  },
  {
    "StartDate": "2023-08-24T14:25:13",
    "EndDate": "2023-10-01T15:13:02",
    "CustomerId": 284
  },
  {
    "StartDate": "2023-12-04T04:02:37",
    "EndDate": "2025-01-17T16:09:52",
    "CustomerId": 19
  },
  {
    "StartDate": "2024-12-06T22:55:43",
    "EndDate": "2025-02-17T04:05:01",
    "CustomerId": 691
  },
  {
    "StartDate": "2025-05-06T21:19:57",
    "EndDate": "2025-06-04T13:05:17",
    "CustomerId": 142
  },
  {
    "StartDate": "2024-05-02T19:42:21",
    "EndDate": "2023-09-06T22:47:59",
    "CustomerId": 251
  },
  {
    "StartDate": "2024-08-31T23:26:59",
    "EndDate": "2024-07-07T20:47:57",
    "CustomerId": 271
  },
  {
    "StartDate": "2024-11-29T03:58:51",
    "EndDate": "2024-03-19T15:41:32",
    "CustomerId": 345
  },
  {
    "StartDate": "2024-05-18T12:27:38",
    "EndDate": "2023-12-08T12:56:16",
    "CustomerId": 284
  },
  {
    "StartDate": "2023-09-16T22:18:26",
    "EndDate": "2025-05-20T05:31:24",
    "CustomerId": 47
  },
  {
    "StartDate": "2025-01-24T16:45:45",
    "EndDate": "2023-12-29T08:20:35",
    "CustomerId": 169
  },
  {
    "StartDate": "2025-02-03T07:09:23",
    "EndDate": "2024-05-28T05:12:48",
    "CustomerId": 41
  },
  {
    "StartDate": "2023-08-07T14:45:28",
    "EndDate": "2024-02-10T13:50:33",
    "CustomerId": 760
  },
  {
    "StartDate": "2024-10-03T01:55:19",
    "EndDate": "2023-09-10T14:06:07",
    "CustomerId": 492
  },
  {
    "StartDate": "2025-05-08T19:25:21",
    "EndDate": "2024-11-23T20:36:21",
    "CustomerId": 128
  },
  {
    "StartDate": "2024-07-13T17:26:57",
    "EndDate": "2023-11-07T14:52:29",
    "CustomerId": 293
  },
  {
    "StartDate": "2025-02-25T18:36:53",
    "EndDate": "2024-07-25T02:17:33",
    "CustomerId": 213
  },
  {
    "StartDate": "2024-07-26T04:10:36",
    "EndDate": "2023-12-31T06:40:28",
    "CustomerId": 711
  },
  {
    "StartDate": "2024-07-04T03:42:56",
    "EndDate": "2024-06-17T16:55:47",
    "CustomerId": 11
  },
  {
    "StartDate": "2024-03-09T01:17:20",
    "EndDate": "2024-01-25T06:05:43",
    "CustomerId": 564
  },
  {
    "StartDate": "2024-12-07T22:37:26",
    "EndDate": "2023-12-16T15:07:58",
    "CustomerId": 426
  },
  {
    "StartDate": "2025-07-06T09:56:03",
    "EndDate": "2024-12-04T09:13:15",
    "CustomerId": 432
  },
  {
    "StartDate": "2024-11-23T00:40:18",
    "EndDate": "2024-05-10T18:39:12",
    "CustomerId": 823
  },
  {
    "StartDate": "2024-07-23T13:47:35",
    "EndDate": "2024-01-30T01:31:51",
    "CustomerId": 582
  },
  {
    "StartDate": "2024-02-12T13:15:58",
    "EndDate": "2023-11-13T12:41:07",
    "CustomerId": 698
  },
  {
    "StartDate": "2024-11-23T17:02:12",
    "EndDate": "2025-04-19T00:40:29",
    "CustomerId": 65
  },
  {
    "StartDate": "2023-11-10T08:19:27",
    "EndDate": "2024-05-07T17:38:11",
    "CustomerId": 514
  },
  {
    "StartDate": "2025-07-12T09:31:36",
    "EndDate": "2024-03-10T22:02:53",
    "CustomerId": 676
  },
  {
    "StartDate": "2024-02-12T16:47:57",
    "EndDate": "2025-03-15T13:54:23",
    "CustomerId": 159
  },
  {
    "StartDate": "2024-03-14T08:16:56",
    "EndDate": "2024-01-17T01:38:00",
    "CustomerId": 411
  },
  {
    "StartDate": "2023-08-18T00:51:45",
    "EndDate": "2024-05-24T01:13:07",
    "CustomerId": 611
  },
  {
    "StartDate": "2024-12-12T09:00:59",
    "EndDate": "2024-07-14T01:46:19",
    "CustomerId": 25
  },
  {
    "StartDate": "2023-12-03T22:50:00",
    "EndDate": "2024-02-13T08:39:46",
    "CustomerId": 388
  },
  {
    "StartDate": "2024-03-05T04:19:09",
    "EndDate": "2024-02-29T02:13:38",
    "CustomerId": 711
  },
  {
    "StartDate": "2025-06-23T14:04:17",
    "EndDate": "2023-11-07T16:48:09",
    "CustomerId": 980
  },
  {
    "StartDate": "2023-11-24T21:55:23",
    "EndDate": "2025-04-01T05:09:37",
    "CustomerId": 355
  },
  {
    "StartDate": "2024-01-13T22:45:24",
    "EndDate": "2024-07-05T08:29:20",
    "CustomerId": 957
  },
  {
    "StartDate": "2023-08-11T21:14:32",
    "EndDate": "2024-07-10T09:49:59",
    "CustomerId": 767
  },
  {
    "StartDate": "2025-07-19T04:00:12",
    "EndDate": "2023-11-28T11:37:50",
    "CustomerId": 880
  },
  {
    "StartDate": "2023-10-04T13:47:35",
    "EndDate": "2023-11-05T01:12:58",
    "CustomerId": 951
  },
  {
    "StartDate": "2024-12-28T12:01:43",
    "EndDate": "2023-11-21T18:17:58",
    "CustomerId": 342
  },
  {
    "StartDate": "2024-05-18T15:41:41",
    "EndDate": "2024-01-03T05:57:23",
    "CustomerId": 127
  },
  {
    "StartDate": "2024-01-31T00:14:33",
    "EndDate": "2024-01-24T08:22:32",
    "CustomerId": 879
  },
  {
    "StartDate": "2024-05-13T19:46:08",
    "EndDate": "2024-06-30T16:43:16",
    "CustomerId": 584
  },
  {
    "StartDate": "2025-04-21T14:33:38",
    "EndDate": "2023-10-30T02:32:08",
    "CustomerId": 82
  },
  {
    "StartDate": "2024-01-19T10:22:10",
    "EndDate": "2024-10-06T14:56:36",
    "CustomerId": 942
  },
  {
    "StartDate": "2024-04-01T19:20:35",
    "EndDate": "2023-10-09T16:11:50",
    "CustomerId": 693
  },
  {
    "StartDate": "2025-07-02T03:42:54",
    "EndDate": "2025-04-20T02:20:02",
    "CustomerId": 731
  },
  {
    "StartDate": "2025-04-04T13:38:10",
    "EndDate": "2025-06-23T16:18:49",
    "CustomerId": 27
  },
  {
    "StartDate": "2023-12-08T20:50:22",
    "EndDate": "2025-02-09T13:12:21",
    "CustomerId": 371
  },
  {
    "StartDate": "2024-06-20T08:07:35",
    "EndDate": "2024-10-23T07:13:16",
    "CustomerId": 961
  },
  {
    "StartDate": "2024-05-23T15:09:05",
    "EndDate": "2024-05-26T17:05:12",
    "CustomerId": 520
  },
  {
    "StartDate": "2024-04-23T17:54:15",
    "EndDate": "2024-12-24T04:37:47",
    "CustomerId": 803
  },
  {
    "StartDate": "2025-04-26T14:05:38",
    "EndDate": "2024-01-31T09:08:59",
    "CustomerId": 932
  },
  {
    "StartDate": "2023-09-05T20:06:56",
    "EndDate": "2023-11-15T17:27:23",
    "CustomerId": 728
  },
  {
    "StartDate": "2024-01-30T18:12:50",
    "EndDate": "2023-09-12T14:03:03",
    "CustomerId": 34
  },
  {
    "StartDate": "2024-07-09T00:17:59",
    "EndDate": "2024-06-27T02:34:32",
    "CustomerId": 139
  },
  {
    "StartDate": "2024-05-14T08:22:18",
    "EndDate": "2024-02-20T17:46:42",
    "CustomerId": 72
  },
  {
    "StartDate": "2024-12-27T02:13:08",
    "EndDate": "2024-02-19T03:55:29",
    "CustomerId": 158
  },
  {
    "StartDate": "2024-11-01T16:35:06",
    "EndDate": "2025-01-22T14:20:19",
    "CustomerId": 303
  },
  {
    "StartDate": "2024-09-24T19:31:00",
    "EndDate": "2024-01-06T13:00:34",
    "CustomerId": 833
  },
  {
    "StartDate": "2025-03-09T13:15:36",
    "EndDate": "2024-08-06T14:01:59",
    "CustomerId": 358
  },
  {
    "StartDate": "2024-08-14T09:36:00",
    "EndDate": "2024-12-15T21:53:08",
    "CustomerId": 826
  },
  {
    "StartDate": "2024-11-14T09:58:08",
    "EndDate": "2024-08-11T08:28:24",
    "CustomerId": 234
  },
  {
    "StartDate": "2025-01-17T09:14:38",
    "EndDate": "2024-03-16T18:10:40",
    "CustomerId": 594
  },
  {
    "StartDate": "2024-08-09T08:28:00",
    "EndDate": "2023-12-04T03:53:18",
    "CustomerId": 672
  },
  {
    "StartDate": "2024-07-11T08:23:49",
    "EndDate": "2023-09-08T06:32:48",
    "CustomerId": 821
  },
  {
    "StartDate": "2025-07-16T08:46:25",
    "EndDate": "2023-10-18T05:56:03",
    "CustomerId": 905
  },
  {
    "StartDate": "2024-06-08T17:46:29",
    "EndDate": "2023-11-13T15:16:36",
    "CustomerId": 794
  },
  {
    "StartDate": "2024-02-19T07:51:26",
    "EndDate": "2024-05-27T13:59:13",
    "CustomerId": 422
  },
  {
    "StartDate": "2024-07-27T02:49:12",
    "EndDate": "2025-04-21T12:34:19",
    "CustomerId": 775
  },
  {
    "StartDate": "2025-05-02T11:33:41",
    "EndDate": "2024-05-13T12:57:26",
    "CustomerId": 669
  },
  {
    "StartDate": "2023-12-23T04:30:10",
    "EndDate": "2025-03-18T00:28:03",
    "CustomerId": 287
  },
  {
    "StartDate": "2023-10-17T07:28:55",
    "EndDate": "2024-02-19T03:41:09",
    "CustomerId": 668
  },
  {
    "StartDate": "2023-08-11T22:50:02",
    "EndDate": "2024-06-11T17:14:38",
    "CustomerId": 927
  },
  {
    "StartDate": "2025-05-01T16:31:40",
    "EndDate": "2024-12-28T07:13:26",
    "CustomerId": 303
  },
  {
    "StartDate": "2024-07-20T02:15:20",
    "EndDate": "2025-05-28T22:13:32",
    "CustomerId": 916
  },
  {
    "StartDate": "2025-05-25T01:08:46",
    "EndDate": "2024-12-29T22:47:40",
    "CustomerId": 281
  },
  {
    "StartDate": "2025-03-10T10:48:43",
    "EndDate": "2024-05-20T22:25:52",
    "CustomerId": 604
  },
  {
    "StartDate": "2024-06-23T22:46:27",
    "EndDate": "2025-02-14T19:48:17",
    "CustomerId": 928
  },
  {
    "StartDate": "2024-10-30T22:24:12",
    "EndDate": "2025-06-25T05:20:36",
    "CustomerId": 821
  },
  {
    "StartDate": "2023-10-31T23:37:09",
    "EndDate": "2025-06-21T03:08:10",
    "CustomerId": 166
  },
  {
    "StartDate": "2024-09-06T01:09:35",
    "EndDate": "2025-06-16T09:40:49",
    "CustomerId": 696
  },
  {
    "StartDate": "2025-02-05T04:28:41",
    "EndDate": "2024-03-25T15:29:58",
    "CustomerId": 20
  },
  {
    "StartDate": "2024-07-15T18:28:54",
    "EndDate": "2025-05-03T20:29:29",
    "CustomerId": 667
  },
  {
    "StartDate": "2025-03-13T21:45:32",
    "EndDate": "2025-06-07T14:02:49",
    "CustomerId": 318
  },
  {
    "StartDate": "2025-06-28T06:12:45",
    "EndDate": "2025-05-13T08:49:15",
    "CustomerId": 579
  },
  {
    "StartDate": "2025-07-15T21:07:59",
    "EndDate": "2025-04-22T03:02:09",
    "CustomerId": 906
  },
  {
    "StartDate": "2024-05-06T05:31:56",
    "EndDate": "2025-01-29T16:38:24",
    "CustomerId": 959
  },
  {
    "StartDate": "2024-05-23T06:05:29",
    "EndDate": "2024-01-23T02:31:57",
    "CustomerId": 494
  },
  {
    "StartDate": "2024-09-02T08:06:38",
    "EndDate": "2024-01-04T19:38:10",
    "CustomerId": 351
  },
  {
    "StartDate": "2024-10-21T18:26:37",
    "EndDate": "2024-06-15T12:19:56",
    "CustomerId": 297
  },
  {
    "StartDate": "2024-03-16T22:32:49",
    "EndDate": "2024-04-28T11:58:48",
    "CustomerId": 894
  },
  {
    "StartDate": "2024-10-06T18:55:10",
    "EndDate": "2025-02-14T17:17:30",
    "CustomerId": 549
  },
  {
    "StartDate": "2025-03-25T20:15:03",
    "EndDate": "2025-04-08T08:06:13",
    "CustomerId": 634
  },
  {
    "StartDate": "2025-01-17T21:23:13",
    "EndDate": "2023-09-12T17:53:41",
    "CustomerId": 529
  },
  {
    "StartDate": "2023-09-10T00:14:38",
    "EndDate": "2025-02-21T00:11:09",
    "CustomerId": 449
  },
  {
    "StartDate": "2025-03-31T17:49:24",
    "EndDate": "2023-12-05T01:38:37",
    "CustomerId": 74
  },
  {
    "StartDate": "2024-04-19T22:36:29",
    "EndDate": "2024-02-11T07:51:21",
    "CustomerId": 967
  },
  {
    "StartDate": "2024-03-09T19:32:45",
    "EndDate": "2025-04-04T12:50:12",
    "CustomerId": 672
  },
  {
    "StartDate": "2025-05-03T13:14:15",
    "EndDate": "2023-08-19T01:33:04",
    "CustomerId": 536
  },
  {
    "StartDate": "2024-11-05T19:52:59",
    "EndDate": "2025-05-01T23:29:37",
    "CustomerId": 546
  },
  {
    "StartDate": "2023-08-01T01:52:20",
    "EndDate": "2024-06-03T21:15:00",
    "CustomerId": 237
  },
  {
    "StartDate": "2024-11-05T03:55:58",
    "EndDate": "2023-12-08T14:07:55",
    "CustomerId": 586
  },
  {
    "StartDate": "2024-12-09T16:54:17",
    "EndDate": "2024-02-29T16:56:14",
    "CustomerId": 151
  },
  {
    "StartDate": "2025-04-08T00:37:47",
    "EndDate": "2025-02-25T18:33:36",
    "CustomerId": 652
  },
  {
    "StartDate": "2023-11-11T00:02:42",
    "EndDate": "2025-03-20T10:47:46",
    "CustomerId": 565
  },
  {
    "StartDate": "2024-11-17T04:10:56",
    "EndDate": "2024-08-23T13:48:23",
    "CustomerId": 621
  },
  {
    "StartDate": "2024-09-01T02:38:03",
    "EndDate": "2024-02-04T21:36:46",
    "CustomerId": 237
  },
  {
    "StartDate": "2024-06-20T20:19:42",
    "EndDate": "2023-11-11T11:24:57",
    "CustomerId": 211
  },
  {
    "StartDate": "2025-01-17T15:20:43",
    "EndDate": "2025-03-20T13:18:14",
    "CustomerId": 923
  },
  {
    "StartDate": "2023-08-11T18:55:08",
    "EndDate": "2023-08-08T21:58:58",
    "CustomerId": 847
  },
  {
    "StartDate": "2025-07-11T02:45:37",
    "EndDate": "2023-08-09T21:12:45",
    "CustomerId": 833
  },
  {
    "StartDate": "2025-02-09T09:22:45",
    "EndDate": "2023-12-16T04:48:59",
    "CustomerId": 727
  },
  {
    "StartDate": "2025-01-23T00:54:24",
    "EndDate": "2023-07-21T22:32:48",
    "CustomerId": 497
  },
  {
    "StartDate": "2025-01-09T08:46:48",
    "EndDate": "2025-02-08T19:33:20",
    "CustomerId": 625
  },
  {
    "StartDate": "2024-08-10T04:48:47",
    "EndDate": "2023-12-30T09:54:56",
    "CustomerId": 961
  },
  {
    "StartDate": "2024-02-07T09:55:12",
    "EndDate": "2023-07-22T03:36:02",
    "CustomerId": 223
  },
  {
    "StartDate": "2025-04-17T21:46:39",
    "EndDate": "2024-09-21T13:30:13",
    "CustomerId": 964
  },
  {
    "StartDate": "2023-10-21T19:55:36",
    "EndDate": "2024-07-10T12:31:27",
    "CustomerId": 8
  },
  {
    "StartDate": "2025-04-01T22:40:31",
    "EndDate": "2024-09-16T09:14:02",
    "CustomerId": 857
  },
  {
    "StartDate": "2024-09-30T09:40:11",
    "EndDate": "2024-11-17T02:58:19",
    "CustomerId": 467
  },
  {
    "StartDate": "2024-06-02T19:18:35",
    "EndDate": "2024-09-14T19:32:12",
    "CustomerId": 415
  },
  {
    "StartDate": "2025-07-03T03:01:28",
    "EndDate": "2023-11-12T10:28:03",
    "CustomerId": 109
  },
  {
    "StartDate": "2024-05-16T16:43:31",
    "EndDate": "2024-09-01T04:53:58",
    "CustomerId": 607
  },
  {
    "StartDate": "2024-10-24T06:57:10",
    "EndDate": "2024-06-12T17:33:17",
    "CustomerId": 651
  },
  {
    "StartDate": "2025-07-06T01:08:13",
    "EndDate": "2025-04-29T18:31:07",
    "CustomerId": 228
  },
  {
    "StartDate": "2024-08-05T06:40:22",
    "EndDate": "2023-08-11T19:15:20",
    "CustomerId": 759
  },
  {
    "StartDate": "2023-07-25T11:52:23",
    "EndDate": "2023-08-12T09:39:38",
    "CustomerId": 899
  },
  {
    "StartDate": "2024-02-26T08:01:56",
    "EndDate": "2025-03-19T10:39:06",
    "CustomerId": 488
  },
  {
    "StartDate": "2024-08-12T22:01:02",
    "EndDate": "2025-01-14T00:37:15",
    "CustomerId": 719
  },
  {
    "StartDate": "2024-09-25T13:23:48",
    "EndDate": "2025-02-20T09:15:16",
    "CustomerId": 634
  },
  {
    "StartDate": "2025-06-12T03:59:31",
    "EndDate": "2025-06-15T12:35:05",
    "CustomerId": 331
  },
  {
    "StartDate": "2024-12-26T08:36:57",
    "EndDate": "2024-04-22T08:46:55",
    "CustomerId": 54
  },
  {
    "StartDate": "2024-10-05T08:36:32",
    "EndDate": "2025-02-20T09:52:38",
    "CustomerId": 549
  },
  {
    "StartDate": "2024-08-05T09:18:01",
    "EndDate": "2024-10-19T16:03:33",
    "CustomerId": 833
  },
  {
    "StartDate": "2024-08-29T21:30:37",
    "EndDate": "2024-11-30T20:21:51",
    "CustomerId": 796
  },
  {
    "StartDate": "2025-04-04T12:10:57",
    "EndDate": "2024-11-18T16:46:44",
    "CustomerId": 968
  },
  {
    "StartDate": "2024-11-21T17:40:14",
    "EndDate": "2025-06-04T04:07:21",
    "CustomerId": 176
  },
  {
    "StartDate": "2023-10-06T08:44:14",
    "EndDate": "2025-07-10T02:38:17",
    "CustomerId": 440
  },
  {
    "StartDate": "2024-07-29T20:01:24",
    "EndDate": "2024-06-21T13:39:22",
    "CustomerId": 832
  },
  {
    "StartDate": "2023-11-21T21:50:03",
    "EndDate": "2024-04-22T02:05:07",
    "CustomerId": 999
  },
  {
    "StartDate": "2023-08-16T21:04:25",
    "EndDate": "2025-03-18T22:15:52",
    "CustomerId": 184
  },
  {
    "StartDate": "2024-04-10T06:26:35",
    "EndDate": "2023-12-10T04:33:09",
    "CustomerId": 875
  },
  {
    "StartDate": "2023-11-13T06:18:47",
    "EndDate": "2023-10-18T10:17:01",
    "CustomerId": 865
  },
  {
    "StartDate": "2024-08-21T08:27:45",
    "EndDate": "2024-10-01T22:00:00",
    "CustomerId": 864
  },
  {
    "StartDate": "2025-01-27T11:36:56",
    "EndDate": "2025-02-05T22:02:52",
    "CustomerId": 859
  },
  {
    "StartDate": "2024-07-10T04:28:03",
    "EndDate": "2025-01-29T16:52:44",
    "CustomerId": 757
  },
  {
    "StartDate": "2024-09-19T22:28:24",
    "EndDate": "2023-08-24T11:00:27",
    "CustomerId": 792
  },
  {
    "StartDate": "2025-01-20T23:45:47",
    "EndDate": "2024-02-04T23:29:59",
    "CustomerId": 75
  },
  {
    "StartDate": "2025-02-24T19:11:40",
    "EndDate": "2025-06-21T03:33:18",
    "CustomerId": 224
  },
  {
    "StartDate": "2024-01-02T13:57:14",
    "EndDate": "2024-09-10T18:14:17",
    "CustomerId": 905
  },
  {
    "StartDate": "2024-04-24T20:13:46",
    "EndDate": "2025-04-30T02:37:27",
    "CustomerId": 114
  },
  {
    "StartDate": "2025-01-12T23:44:40",
    "EndDate": "2023-09-29T06:01:56",
    "CustomerId": 706
  },
  {
    "StartDate": "2023-09-16T03:19:50",
    "EndDate": "2024-12-04T18:35:50",
    "CustomerId": 872
  },
  {
    "StartDate": "2024-05-29T18:40:23",
    "EndDate": "2023-08-23T00:30:01",
    "CustomerId": 640
  },
  {
    "StartDate": "2024-05-22T05:03:58",
    "EndDate": "2024-04-16T07:44:57",
    "CustomerId": 475
  },
  {
    "StartDate": "2024-10-25T19:36:34",
    "EndDate": "2024-08-02T13:01:32",
    "CustomerId": 599
  },
  {
    "StartDate": "2025-01-23T17:26:04",
    "EndDate": "2024-06-05T01:26:44",
    "CustomerId": 110
  },
  {
    "StartDate": "2024-05-13T12:48:05",
    "EndDate": "2024-04-12T09:40:40",
    "CustomerId": 947
  },
  {
    "StartDate": "2025-04-19T23:31:51",
    "EndDate": "2024-04-30T10:54:52",
    "CustomerId": 870
  },
  {
    "StartDate": "2024-02-19T19:34:16",
    "EndDate": "2024-09-04T10:24:25",
    "CustomerId": 170
  },
  {
    "StartDate": "2025-03-21T03:22:58",
    "EndDate": "2024-01-22T08:38:42",
    "CustomerId": 426
  },
  {
    "StartDate": "2024-03-02T14:08:40",
    "EndDate": "2023-10-17T11:10:48",
    "CustomerId": 810
  },
  {
    "StartDate": "2024-10-20T04:50:08",
    "EndDate": "2023-08-30T13:23:54",
    "CustomerId": 763
  },
  {
    "StartDate": "2025-05-16T04:44:17",
    "EndDate": "2025-06-14T05:42:43",
    "CustomerId": 900
  },
  {
    "StartDate": "2024-01-10T23:37:21",
    "EndDate": "2023-12-28T05:29:29",
    "CustomerId": 520
  },
  {
    "StartDate": "2024-09-07T22:21:21",
    "EndDate": "2025-06-20T16:36:38",
    "CustomerId": 183
  },
  {
    "StartDate": "2024-08-26T15:05:52",
    "EndDate": "2024-09-29T13:22:14",
    "CustomerId": 993
  },
  {
    "StartDate": "2024-01-20T15:09:15",
    "EndDate": "2024-11-30T23:11:45",
    "CustomerId": 729
  },
  {
    "StartDate": "2023-10-11T17:46:57",
    "EndDate": "2025-01-22T14:40:11",
    "CustomerId": 569
  },
  {
    "StartDate": "2023-11-02T21:21:42",
    "EndDate": "2024-01-07T10:41:31",
    "CustomerId": 280
  },
  {
    "StartDate": "2024-03-22T19:32:35",
    "EndDate": "2024-04-28T12:57:15",
    "CustomerId": 342
  },
  {
    "StartDate": "2023-10-21T03:21:36",
    "EndDate": "2024-07-14T20:42:54",
    "CustomerId": 622
  },
  {
    "StartDate": "2023-12-06T22:25:31",
    "EndDate": "2025-02-06T06:34:27",
    "CustomerId": 499
  },
  {
    "StartDate": "2024-09-22T15:12:56",
    "EndDate": "2024-06-05T20:53:36",
    "CustomerId": 530
  },
  {
    "StartDate": "2024-10-06T20:31:30",
    "EndDate": "2024-07-15T11:30:22",
    "CustomerId": 670
  },
  {
    "StartDate": "2024-10-06T06:29:30",
    "EndDate": "2024-06-12T07:21:27",
    "CustomerId": 820
  },
  {
    "StartDate": "2024-02-09T10:40:04",
    "EndDate": "2024-04-19T11:59:01",
    "CustomerId": 80
  },
  {
    "StartDate": "2024-10-22T01:14:01",
    "EndDate": "2023-08-23T12:38:05",
    "CustomerId": 371
  },
  {
    "StartDate": "2023-08-26T05:51:32",
    "EndDate": "2023-09-07T15:15:44",
    "CustomerId": 641
  },
  {
    "StartDate": "2024-01-04T14:14:19",
    "EndDate": "2024-03-25T13:29:53",
    "CustomerId": 343
  },
  {
    "StartDate": "2025-05-02T03:13:15",
    "EndDate": "2024-09-30T06:17:49",
    "CustomerId": 644
  },
  {
    "StartDate": "2024-01-07T20:16:25",
    "EndDate": "2024-09-11T19:22:28",
    "CustomerId": 818
  },
  {
    "StartDate": "2025-04-21T21:40:50",
    "EndDate": "2025-07-07T19:03:36",
    "CustomerId": 169
  },
  {
    "StartDate": "2024-09-16T18:49:11",
    "EndDate": "2023-10-05T05:46:45",
    "CustomerId": 420
  },
  {
    "StartDate": "2024-06-30T00:50:18",
    "EndDate": "2025-04-02T04:17:21",
    "CustomerId": 573
  },
  {
    "StartDate": "2025-04-10T06:06:51",
    "EndDate": "2024-08-14T03:03:41",
    "CustomerId": 237
  },
  {
    "StartDate": "2025-04-06T16:12:57",
    "EndDate": "2024-06-15T08:58:56",
    "CustomerId": 234
  },
  {
    "StartDate": "2024-01-11T15:44:38",
    "EndDate": "2024-02-09T00:40:56",
    "CustomerId": 502
  },
  {
    "StartDate": "2025-04-22T15:01:46",
    "EndDate": "2024-05-09T18:56:07",
    "CustomerId": 953
  },
  {
    "StartDate": "2024-05-09T04:30:03",
    "EndDate": "2024-01-11T15:28:32",
    "CustomerId": 671
  },
  {
    "StartDate": "2025-06-27T02:53:09",
    "EndDate": "2024-11-27T10:04:17",
    "CustomerId": 569
  },
  {
    "StartDate": "2023-10-08T17:54:58",
    "EndDate": "2025-05-25T00:52:11",
    "CustomerId": 37
  },
  {
    "StartDate": "2025-02-03T10:27:31",
    "EndDate": "2023-08-11T05:24:51",
    "CustomerId": 419
  },
  {
    "StartDate": "2023-10-12T22:15:29",
    "EndDate": "2024-03-02T00:45:10",
    "CustomerId": 751
  },
  {
    "StartDate": "2023-08-08T12:15:09",
    "EndDate": "2025-02-04T19:23:49",
    "CustomerId": 877
  },
  {
    "StartDate": "2024-02-14T09:49:17",
    "EndDate": "2023-09-08T11:13:33",
    "CustomerId": 381
  },
  {
    "StartDate": "2023-07-28T17:04:52",
    "EndDate": "2024-02-25T09:54:11",
    "CustomerId": 760
  },
  {
    "StartDate": "2024-02-10T03:55:14",
    "EndDate": "2023-11-21T10:15:16",
    "CustomerId": 4
  },
  {
    "StartDate": "2024-01-28T05:32:29",
    "EndDate": "2025-04-22T07:17:20",
    "CustomerId": 735
  },
  {
    "StartDate": "2023-09-27T14:59:34",
    "EndDate": "2023-09-08T21:08:46",
    "CustomerId": 567
  },
  {
    "StartDate": "2023-08-22T08:26:42",
    "EndDate": "2025-07-07T02:03:05",
    "CustomerId": 277
  },
  {
    "StartDate": "2024-03-21T09:19:49",
    "EndDate": "2023-12-13T02:13:17",
    "CustomerId": 768
  },
  {
    "StartDate": "2023-12-23T23:46:20",
    "EndDate": "2024-04-09T21:58:28",
    "CustomerId": 349
  },
  {
    "StartDate": "2023-09-19T21:16:23",
    "EndDate": "2024-08-15T06:29:04",
    "CustomerId": 114
  },
  {
    "StartDate": "2024-03-10T23:06:15",
    "EndDate": "2025-07-15T22:09:22",
    "CustomerId": 266
  },
  {
    "StartDate": "2023-08-17T18:04:12",
    "EndDate": "2025-03-26T05:09:26",
    "CustomerId": 190
  },
  {
    "StartDate": "2025-03-16T11:13:29",
    "EndDate": "2024-04-11T23:09:22",
    "CustomerId": 927
  },
  {
    "StartDate": "2024-12-08T13:54:18",
    "EndDate": "2024-10-30T23:35:22",
    "CustomerId": 985
  },
  {
    "StartDate": "2025-07-18T15:23:05",
    "EndDate": "2025-05-14T01:17:48",
    "CustomerId": 883
  },
  {
    "StartDate": "2023-11-10T03:07:28",
    "EndDate": "2025-02-12T13:23:20",
    "CustomerId": 143
  },
  {
    "StartDate": "2024-12-30T13:28:54",
    "EndDate": "2024-03-01T05:52:40",
    "CustomerId": 770
  },
  {
    "StartDate": "2024-12-24T22:29:29",
    "EndDate": "2024-05-12T07:04:25",
    "CustomerId": 529
  },
  {
    "StartDate": "2023-08-28T14:45:15",
    "EndDate": "2024-11-29T17:43:20",
    "CustomerId": 595
  },
  {
    "StartDate": "2025-05-12T14:46:07",
    "EndDate": "2024-11-22T11:34:38",
    "CustomerId": 976
  },
  {
    "StartDate": "2025-06-20T11:32:07",
    "EndDate": "2023-11-10T11:59:41",
    "CustomerId": 407
  },
  {
    "StartDate": "2023-09-24T08:24:37",
    "EndDate": "2024-06-02T15:42:15",
    "CustomerId": 72
  },
  {
    "StartDate": "2025-03-06T22:55:41",
    "EndDate": "2024-06-24T01:05:21",
    "CustomerId": 962
  },
  {
    "StartDate": "2024-03-20T11:38:05",
    "EndDate": "2023-09-23T05:48:23",
    "CustomerId": 561
  },
  {
    "StartDate": "2025-03-06T21:16:25",
    "EndDate": "2024-10-22T22:02:56",
    "CustomerId": 853
  },
  {
    "StartDate": "2024-01-09T12:53:42",
    "EndDate": "2025-01-30T07:11:10",
    "CustomerId": 371
  },
  {
    "StartDate": "2024-01-12T09:12:27",
    "EndDate": "2025-04-08T06:49:06",
    "CustomerId": 197
  },
  {
    "StartDate": "2024-12-25T23:54:38",
    "EndDate": "2024-09-03T08:59:18",
    "CustomerId": 229
  },
  {
    "StartDate": "2025-03-26T11:21:51",
    "EndDate": "2024-07-03T21:10:58",
    "CustomerId": 850
  },
  {
    "StartDate": "2024-05-20T10:21:40",
    "EndDate": "2024-05-16T20:58:06",
    "CustomerId": 759
  },
  {
    "StartDate": "2024-03-02T21:55:42",
    "EndDate": "2024-06-14T22:21:38",
    "CustomerId": 250
  },
  {
    "StartDate": "2024-09-28T13:14:24",
    "EndDate": "2024-09-27T11:13:10",
    "CustomerId": 443
  },
  {
    "StartDate": "2023-11-04T21:28:14",
    "EndDate": "2024-06-19T14:14:51",
    "CustomerId": 195
  },
  {
    "StartDate": "2025-03-24T06:55:47",
    "EndDate": "2025-02-26T00:13:10",
    "CustomerId": 995
  },
  {
    "StartDate": "2023-12-09T01:40:22",
    "EndDate": "2024-12-19T17:19:08",
    "CustomerId": 76
  },
  {
    "StartDate": "2024-01-25T21:27:04",
    "EndDate": "2023-08-20T13:22:13",
    "CustomerId": 274
  },
  {
    "StartDate": "2024-04-25T00:53:46",
    "EndDate": "2024-10-31T03:17:55",
    "CustomerId": 687
  },
  {
    "StartDate": "2024-09-20T11:39:29",
    "EndDate": "2025-05-04T10:18:18",
    "CustomerId": 458
  },
  {
    "StartDate": "2023-08-05T10:05:52",
    "EndDate": "2023-08-17T03:44:33",
    "CustomerId": 820
  },
  {
    "StartDate": "2024-08-19T06:56:31",
    "EndDate": "2023-12-03T12:48:39",
    "CustomerId": 55
  },
  {
    "StartDate": "2024-05-31T06:20:24",
    "EndDate": "2023-10-18T03:21:20",
    "CustomerId": 703
  },
  {
    "StartDate": "2025-01-18T23:04:41",
    "EndDate": "2023-11-25T03:50:12",
    "CustomerId": 718
  },
  {
    "StartDate": "2024-12-22T13:37:26",
    "EndDate": "2024-04-19T15:48:19",
    "CustomerId": 465
  },
  {
    "StartDate": "2024-01-04T13:00:37",
    "EndDate": "2025-02-10T10:57:59",
    "CustomerId": 638
  },
  {
    "StartDate": "2024-06-30T09:09:10",
    "EndDate": "2025-04-20T01:52:34",
    "CustomerId": 251
  },
  {
    "StartDate": "2025-04-26T07:03:15",
    "EndDate": "2025-05-10T23:30:13",
    "CustomerId": 502
  },
  {
    "StartDate": "2023-09-20T11:27:07",
    "EndDate": "2024-06-09T00:12:36",
    "CustomerId": 959
  },
  {
    "StartDate": "2024-02-08T02:49:15",
    "EndDate": "2024-10-01T22:16:23",
    "CustomerId": 177
  },
  {
    "StartDate": "2024-02-20T00:28:29",
    "EndDate": "2025-04-15T20:57:54",
    "CustomerId": 673
  },
  {
    "StartDate": "2024-01-18T11:56:56",
    "EndDate": "2024-09-18T09:09:41",
    "CustomerId": 233
  },
  {
    "StartDate": "2023-08-13T15:01:08",
    "EndDate": "2024-10-31T05:33:30",
    "CustomerId": 19
  },
  {
    "StartDate": "2025-01-19T07:38:00",
    "EndDate": "2023-12-25T16:13:12",
    "CustomerId": 219
  },
  {
    "StartDate": "2024-04-30T22:09:04",
    "EndDate": "2024-02-06T17:28:01",
    "CustomerId": 788
  },
  {
    "StartDate": "2025-05-08T12:57:16",
    "EndDate": "2024-04-21T07:15:12",
    "CustomerId": 722
  },
  {
    "StartDate": "2024-01-27T15:59:55",
    "EndDate": "2024-04-27T12:52:11",
    "CustomerId": 154
  },
  {
    "StartDate": "2024-10-19T18:32:57",
    "EndDate": "2023-08-27T06:41:26",
    "CustomerId": 437
  },
  {
    "StartDate": "2025-02-16T02:34:37",
    "EndDate": "2024-12-08T19:27:14",
    "CustomerId": 295
  },
  {
    "StartDate": "2025-05-17T13:36:19",
    "EndDate": "2024-09-07T07:57:32",
    "CustomerId": 436
  },
  {
    "StartDate": "2023-08-31T14:27:56",
    "EndDate": "2024-09-20T23:27:26",
    "CustomerId": 255
  },
  {
    "StartDate": "2023-10-15T12:38:26",
    "EndDate": "2025-07-01T19:08:23",
    "CustomerId": 889
  },
  {
    "StartDate": "2024-08-12T12:36:46",
    "EndDate": "2025-02-27T06:29:35",
    "CustomerId": 907
  },
  {
    "StartDate": "2025-01-17T13:13:44",
    "EndDate": "2025-05-16T12:19:35",
    "CustomerId": 551
  },
  {
    "StartDate": "2024-09-13T23:02:15",
    "EndDate": "2023-08-25T03:43:20",
    "CustomerId": 368
  },
  {
    "StartDate": "2024-02-05T05:15:48",
    "EndDate": "2025-05-06T21:29:26",
    "CustomerId": 150
  },
  {
    "StartDate": "2025-06-29T11:06:31",
    "EndDate": "2024-11-28T18:54:40",
    "CustomerId": 494
  },
  {
    "StartDate": "2024-10-28T18:45:05",
    "EndDate": "2024-11-29T00:23:26",
    "CustomerId": 645
  },
  {
    "StartDate": "2023-12-10T09:07:39",
    "EndDate": "2024-11-02T20:44:07",
    "CustomerId": 418
  },
  {
    "StartDate": "2023-08-04T22:27:56",
    "EndDate": "2024-08-05T10:04:44",
    "CustomerId": 861
  },
  {
    "StartDate": "2024-09-27T20:51:00",
    "EndDate": "2024-01-30T18:48:04",
    "CustomerId": 74
  },
  {
    "StartDate": "2023-12-25T00:41:56",
    "EndDate": "2025-01-29T11:25:45",
    "CustomerId": 194
  },
  {
    "StartDate": "2025-05-08T16:17:43",
    "EndDate": "2024-03-10T19:03:24",
    "CustomerId": 357
  },
  {
    "StartDate": "2023-12-20T20:33:18",
    "EndDate": "2024-06-01T13:18:06",
    "CustomerId": 266
  },
  {
    "StartDate": "2024-04-08T07:18:28",
    "EndDate": "2024-06-26T23:15:55",
    "CustomerId": 529
  },
  {
    "StartDate": "2024-02-18T23:35:27",
    "EndDate": "2024-05-04T17:35:35",
    "CustomerId": 47
  },
  {
    "StartDate": "2024-12-31T18:03:48",
    "EndDate": "2025-01-19T08:35:18",
    "CustomerId": 934
  },
  {
    "StartDate": "2024-05-23T15:19:24",
    "EndDate": "2024-02-05T20:30:01",
    "CustomerId": 714
  },
  {
    "StartDate": "2024-12-01T05:02:07",
    "EndDate": "2025-05-18T06:52:07",
    "CustomerId": 816
  },
  {
    "StartDate": "2023-09-22T09:55:48",
    "EndDate": "2024-11-17T07:02:58",
    "CustomerId": 721
  },
  {
    "StartDate": "2024-01-11T05:10:11",
    "EndDate": "2024-03-07T00:51:55",
    "CustomerId": 99
  },
  {
    "StartDate": "2024-10-10T05:49:01",
    "EndDate": "2024-12-26T07:42:35",
    "CustomerId": 553
  },
  {
    "StartDate": "2025-01-31T20:41:03",
    "EndDate": "2025-05-24T14:59:48",
    "CustomerId": 845
  },
  {
    "StartDate": "2025-05-22T16:03:50",
    "EndDate": "2025-06-18T06:48:56",
    "CustomerId": 861
  },
  {
    "StartDate": "2025-03-09T07:24:17",
    "EndDate": "2024-12-11T20:51:00",
    "CustomerId": 935
  },
  {
    "StartDate": "2023-11-12T16:16:39",
    "EndDate": "2024-03-28T10:21:22",
    "CustomerId": 64
  },
  {
    "StartDate": "2024-11-21T18:33:19",
    "EndDate": "2025-01-08T11:54:41",
    "CustomerId": 429
  },
  {
    "StartDate": "2023-11-28T07:29:26",
    "EndDate": "2025-05-19T01:47:33",
    "CustomerId": 812
  },
  {
    "StartDate": "2024-07-17T21:14:00",
    "EndDate": "2024-05-01T05:37:20",
    "CustomerId": 460
  },
  {
    "StartDate": "2024-08-12T07:56:35",
    "EndDate": "2025-03-15T08:22:47",
    "CustomerId": 256
  },
  {
    "StartDate": "2024-06-17T04:13:35",
    "EndDate": "2024-10-09T06:30:24",
    "CustomerId": 248
  },
  {
    "StartDate": "2025-02-10T04:17:07",
    "EndDate": "2024-02-14T05:47:25",
    "CustomerId": 229
  },
  {
    "StartDate": "2025-05-24T15:24:22",
    "EndDate": "2024-12-27T07:09:59",
    "CustomerId": 137
  },
  {
    "StartDate": "2025-01-25T09:16:45",
    "EndDate": "2024-07-12T19:15:40",
    "CustomerId": 849
  },
  {
    "StartDate": "2024-02-03T21:21:21",
    "EndDate": "2025-07-14T22:34:14",
    "CustomerId": 492
  },
  {
    "StartDate": "2025-01-07T20:46:16",
    "EndDate": "2025-07-07T02:04:49",
    "CustomerId": 222
  },
  {
    "StartDate": "2024-01-04T17:28:14",
    "EndDate": "2024-02-12T21:50:19",
    "CustomerId": 546
  },
  {
    "StartDate": "2025-01-27T06:30:43",
    "EndDate": "2025-06-12T10:13:55",
    "CustomerId": 276
  },
  {
    "StartDate": "2024-07-03T05:35:00",
    "EndDate": "2024-04-26T11:56:37",
    "CustomerId": 874
  },
  {
    "StartDate": "2024-06-28T04:58:57",
    "EndDate": "2024-10-03T09:09:49",
    "CustomerId": 815
  },
  {
    "StartDate": "2025-01-09T11:03:19",
    "EndDate": "2025-04-08T23:45:30",
    "CustomerId": 717
  },
  {
    "StartDate": "2025-03-21T09:16:40",
    "EndDate": "2025-01-09T22:45:56",
    "CustomerId": 92
  },
  {
    "StartDate": "2023-09-04T13:07:06",
    "EndDate": "2023-08-31T22:20:09",
    "CustomerId": 663
  },
  {
    "StartDate": "2025-01-22T17:59:08",
    "EndDate": "2024-12-14T08:04:28",
    "CustomerId": 323
  },
  {
    "StartDate": "2024-10-28T21:45:54",
    "EndDate": "2023-12-13T14:50:46",
    "CustomerId": 400
  },
  {
    "StartDate": "2023-12-14T22:53:53",
    "EndDate": "2023-09-03T11:27:22",
    "CustomerId": 930
  },
  {
    "StartDate": "2024-07-29T19:54:48",
    "EndDate": "2023-11-27T16:53:21",
    "CustomerId": 950
  },
  {
    "StartDate": "2024-10-20T17:48:40",
    "EndDate": "2025-01-21T19:50:10",
    "CustomerId": 691
  },
  {
    "StartDate": "2024-02-03T20:27:10",
    "EndDate": "2023-12-19T15:59:28",
    "CustomerId": 515
  },
  {
    "StartDate": "2023-11-06T15:46:04",
    "EndDate": "2024-07-25T11:48:02",
    "CustomerId": 821
  },
  {
    "StartDate": "2023-10-01T09:14:13",
    "EndDate": "2024-12-21T07:14:31",
    "CustomerId": 754
  },
  {
    "StartDate": "2025-01-11T02:13:21",
    "EndDate": "2025-07-15T12:03:23",
    "CustomerId": 775
  },
  {
    "StartDate": "2025-02-18T16:16:18",
    "EndDate": "2024-12-09T19:14:00",
    "CustomerId": 572
  },
  {
    "StartDate": "2025-01-28T04:46:17",
    "EndDate": "2024-12-06T17:04:59",
    "CustomerId": 55
  },
  {
    "StartDate": "2024-10-10T22:38:25",
    "EndDate": "2025-07-04T00:51:45",
    "CustomerId": 268
  },
  {
    "StartDate": "2024-01-24T14:53:40",
    "EndDate": "2023-12-10T07:41:44",
    "CustomerId": 131
  },
  {
    "StartDate": "2023-07-25T21:56:35",
    "EndDate": "2024-03-19T01:34:08",
    "CustomerId": 308
  },
  {
    "StartDate": "2024-03-23T20:46:16",
    "EndDate": "2023-12-11T09:54:08",
    "CustomerId": 332
  },
  {
    "StartDate": "2023-09-16T01:44:26",
    "EndDate": "2023-09-20T08:44:38",
    "CustomerId": 464
  },
  {
    "StartDate": "2025-01-23T16:48:39",
    "EndDate": "2025-01-19T07:52:30",
    "CustomerId": 551
  },
  {
    "StartDate": "2024-12-08T12:04:56",
    "EndDate": "2025-04-06T11:00:01",
    "CustomerId": 47
  },
  {
    "StartDate": "2024-03-24T07:44:58",
    "EndDate": "2024-09-25T07:07:57",
    "CustomerId": 450
  },
  {
    "StartDate": "2024-07-06T06:25:10",
    "EndDate": "2024-07-05T08:36:13",
    "CustomerId": 951
  },
  {
    "StartDate": "2024-11-12T00:37:59",
    "EndDate": "2024-08-26T22:50:58",
    "CustomerId": 816
  },
  {
    "StartDate": "2024-03-17T15:10:17",
    "EndDate": "2024-10-30T05:05:59",
    "CustomerId": 539
  },
  {
    "StartDate": "2025-06-06T21:01:17",
    "EndDate": "2024-10-08T03:34:52",
    "CustomerId": 479
  },
  {
    "StartDate": "2025-05-19T10:56:26",
    "EndDate": "2023-09-08T10:25:43",
    "CustomerId": 89
  },
  {
    "StartDate": "2025-05-09T19:20:36",
    "EndDate": "2024-02-20T03:41:45",
    "CustomerId": 584
  },
  {
    "StartDate": "2024-11-04T18:43:37",
    "EndDate": "2024-09-06T00:50:32",
    "CustomerId": 777
  },
  {
    "StartDate": "2024-09-04T12:59:42",
    "EndDate": "2023-12-28T22:56:12",
    "CustomerId": 309
  },
  {
    "StartDate": "2024-09-22T13:07:41",
    "EndDate": "2023-08-01T16:16:50",
    "CustomerId": 241
  },
  {
    "StartDate": "2025-04-20T02:05:14",
    "EndDate": "2024-05-24T01:48:55",
    "CustomerId": 899
  },
  {
    "StartDate": "2024-03-09T18:17:36",
    "EndDate": "2023-07-28T05:29:55",
    "CustomerId": 127
  },
  {
    "StartDate": "2024-09-27T07:19:12",
    "EndDate": "2024-09-06T11:53:48",
    "CustomerId": 55
  },
  {
    "StartDate": "2025-05-24T02:15:31",
    "EndDate": "2025-06-09T08:54:20",
    "CustomerId": 457
  },
  {
    "StartDate": "2023-08-20T18:31:02",
    "EndDate": "2024-01-09T06:39:34",
    "CustomerId": 387
  },
  {
    "StartDate": "2024-04-23T19:54:35",
    "EndDate": "2025-05-16T04:07:04",
    "CustomerId": 101
  },
  {
    "StartDate": "2023-10-10T08:50:16",
    "EndDate": "2024-11-18T23:44:09",
    "CustomerId": 988
  },
  {
    "StartDate": "2024-07-15T00:35:44",
    "EndDate": "2025-06-04T03:46:49",
    "CustomerId": 683
  },
  {
    "StartDate": "2023-10-24T19:43:08",
    "EndDate": "2024-02-27T07:29:46",
    "CustomerId": 530
  },
  {
    "StartDate": "2023-10-18T10:24:51",
    "EndDate": "2024-10-21T01:36:04",
    "CustomerId": 419
  },
  {
    "StartDate": "2025-05-13T14:59:29",
    "EndDate": "2025-05-13T23:07:25",
    "CustomerId": 984
  },
  {
    "StartDate": "2023-10-08T21:48:13",
    "EndDate": "2025-07-06T12:13:54",
    "CustomerId": 922
  },
  {
    "StartDate": "2024-01-22T04:24:40",
    "EndDate": "2024-11-06T16:23:57",
    "CustomerId": 641
  },
  {
    "StartDate": "2024-06-22T10:58:07",
    "EndDate": "2024-11-16T09:54:13",
    "CustomerId": 162
  },
  {
    "StartDate": "2025-03-30T18:02:01",
    "EndDate": "2023-09-15T02:45:36",
    "CustomerId": 406
  },
  {
    "StartDate": "2024-12-04T02:54:24",
    "EndDate": "2023-12-05T16:28:51",
    "CustomerId": 916
  },
  {
    "StartDate": "2024-10-27T21:21:25",
    "EndDate": "2025-03-10T11:15:25",
    "CustomerId": 210
  },
  {
    "StartDate": "2025-04-12T12:45:54",
    "EndDate": "2024-12-22T14:28:12",
    "CustomerId": 644
  },
  {
    "StartDate": "2024-09-30T17:43:11",
    "EndDate": "2024-08-13T16:26:45",
    "CustomerId": 759
  },
  {
    "StartDate": "2023-12-03T10:14:52",
    "EndDate": "2023-09-08T19:14:48",
    "CustomerId": 976
  },
  {
    "StartDate": "2025-01-27T15:28:06",
    "EndDate": "2025-03-11T11:36:09",
    "CustomerId": 872
  },
  {
    "StartDate": "2024-08-25T14:08:48",
    "EndDate": "2024-03-18T06:23:16",
    "CustomerId": 668
  },
  {
    "StartDate": "2024-09-04T16:54:44",
    "EndDate": "2024-09-11T17:39:20",
    "CustomerId": 322
  },
  {
    "StartDate": "2025-05-25T23:02:16",
    "EndDate": "2025-06-18T10:26:51",
    "CustomerId": 540
  },
  {
    "StartDate": "2023-07-25T00:06:59",
    "EndDate": "2023-11-24T03:51:49",
    "CustomerId": 694
  },
  {
    "StartDate": "2024-12-12T20:05:24",
    "EndDate": "2023-08-27T20:39:16",
    "CustomerId": 942
  },
  {
    "StartDate": "2024-10-26T00:16:58",
    "EndDate": "2024-12-13T19:42:56",
    "CustomerId": 678
  },
  {
    "StartDate": "2023-12-14T11:01:04",
    "EndDate": "2024-08-18T16:58:35",
    "CustomerId": 154
  },
  {
    "StartDate": "2025-06-24T04:53:09",
    "EndDate": "2025-01-27T07:19:26",
    "CustomerId": 104
  },
  {
    "StartDate": "2025-02-19T02:41:31",
    "EndDate": "2024-07-15T12:29:50",
    "CustomerId": 752
  },
  {
    "StartDate": "2024-04-02T00:34:15",
    "EndDate": "2024-01-24T09:00:23",
    "CustomerId": 837
  },
  {
    "StartDate": "2025-01-03T01:40:04",
    "EndDate": "2024-03-04T21:13:35",
    "CustomerId": 209
  },
  {
    "StartDate": "2023-12-30T02:47:12",
    "EndDate": "2023-12-29T14:55:53",
    "CustomerId": 992
  },
  {
    "StartDate": "2024-10-22T21:26:19",
    "EndDate": "2024-03-05T10:33:56",
    "CustomerId": 339
  },
  {
    "StartDate": "2025-05-25T00:07:59",
    "EndDate": "2024-10-27T16:43:50",
    "CustomerId": 266
  },
  {
    "StartDate": "2023-12-24T04:24:48",
    "EndDate": "2024-10-09T01:57:50",
    "CustomerId": 488
  },
  {
    "StartDate": "2025-03-13T21:50:19",
    "EndDate": "2024-03-04T03:25:07",
    "CustomerId": 766
  },
  {
    "StartDate": "2024-04-03T16:33:32",
    "EndDate": "2024-12-18T22:37:05",
    "CustomerId": 836
  },
  {
    "StartDate": "2023-09-06T06:49:05",
    "EndDate": "2023-09-30T07:28:08",
    "CustomerId": 891
  },
  {
    "StartDate": "2023-10-08T07:58:53",
    "EndDate": "2024-06-23T12:52:21",
    "CustomerId": 723
  },
  {
    "StartDate": "2024-01-04T14:51:14",
    "EndDate": "2024-05-17T16:04:52",
    "CustomerId": 561
  },
  {
    "StartDate": "2024-04-15T04:45:11",
    "EndDate": "2025-04-10T03:04:12",
    "CustomerId": 397
  },
  {
    "StartDate": "2024-08-12T06:13:14",
    "EndDate": "2025-03-21T00:31:52",
    "CustomerId": 188
  },
  {
    "StartDate": "2024-03-23T19:04:00",
    "EndDate": "2024-03-03T01:30:13",
    "CustomerId": 771
  },
  {
    "StartDate": "2025-07-19T07:47:45",
    "EndDate": "2024-06-14T20:53:36",
    "CustomerId": 28
  },
  {
    "StartDate": "2025-06-30T15:25:20",
    "EndDate": "2025-06-07T08:26:44",
    "CustomerId": 734
  },
  {
    "StartDate": "2024-10-12T22:48:24",
    "EndDate": "2024-08-08T21:17:21",
    "CustomerId": 387
  },
  {
    "StartDate": "2024-10-12T11:25:01",
    "EndDate": "2024-08-13T04:42:01",
    "CustomerId": 117
  },
  {
    "StartDate": "2024-05-15T16:00:46",
    "EndDate": "2025-03-04T15:36:11",
    "CustomerId": 901
  },
  {
    "StartDate": "2025-04-03T10:08:14",
    "EndDate": "2024-02-25T15:10:54",
    "CustomerId": 884
  }
]